{
  "_fv": 24,
  "_type": "food",
  "definition": {
    "renderType": 0,
    "texture": "coffee_texture",
    "customModelName": "Normal",
    "name": "Coffee",
    "rarity": "COMMON",
    "specialInfo": [],
    "creativeTab": {
      "value": "CUSTOM:CoffeesCreaturesTab"
    },
    "stackSize": 64,
    "nutritionalValue": 4,
    "saturation": 0.3,
    "eatingSpeed": 32,
    "resultItem": {
      "value": ""
    },
    "forDogs": false,
    "isAlwaysEdible": true,
    "animation": "drink",
    "hasGlow": false,
    "onEaten": {
      "name": "CoffeeFoodEaten"
    }
  }
}